LICENSE
README.rst
setup.py
GLRParser/__init__.py
GLRParser/grammar.py
GLRParser/main.py
GLRParser/morpher.py
GLRParser/parser.py
GLRParser/tree.py
GLRParser.egg-info/PKG-INFO
GLRParser.egg-info/SOURCES.txt
GLRParser.egg-info/dependency_links.txt
GLRParser.egg-info/top_level.txt
GLRParser/grm/eng_ger.in.txt
GLRParser/grm/eng_ger.out.txt
GLRParser/grm/feature.grm
GLRParser/grm/ger_eng.in.txt
GLRParser/grm/ger_eng.out.txt
GLRParser/grm/german.grm
GLRParser/grm/main.grm
GLRParser/grm/main.grmc
GLRParser/grm/main.in.txt
GLRParser/grm/main.out.txt
GLRParser/grm/np.in.txt
GLRParser/grm/numbers.grm
GLRParser/grm/simple.grm
GLRParser/grm/simple_trans.grm
GLRParser/grm/tenses.grm
GLRParser/grm/tenses.in.txt
GLRParser/grm/tenses.out.txt
GLRParser/grm/time_adv.grm
GLRParser/grm/vp.in.txt
GLRParser/grm/vp_inc.grm