Metadata-Version: 2.1
Name: GLRParser
Version: 0.3.25
Summary: A GLR Parser for Natural Language Processing and Translation
Home-page: https://github.com/mdolgun/GLRParser
Author: Mehmet Dolgun
Author-email: m.dolgun@yahoo.com
License: MIT
Keywords: NLP MachineTranslation Parser GLR Turkish
Platform: UNKNOWN
Classifier: Development Status :: 3 - Alpha
Classifier: License :: OSI Approved :: MIT License
Classifier: Programming Language :: Python :: 3.7
Classifier: Programming Language :: Python :: 3.8
Classifier: Programming Language :: Python :: 3.9
Classifier: Programming Language :: Python :: 3.10
Classifier: Programming Language :: Python :: 3.11
License-File: LICENSE
